tikreg/__init__.py
tikreg/defaults.cfg
tikreg/kernels.py
tikreg/models.py
tikreg/priors.py
tikreg/spatial_priors.py
tikreg/svd_dgesvd.py
tikreg/temporal_priors.py
tikreg/utils.py
tikreg-0.0.1.dist-info/LICENSE
tikreg-0.0.1.dist-info/METADATA
tikreg-0.0.1.dist-info/WHEEL
tikreg-0.0.1.dist-info/top_level.txt
tikreg-0.0.1.dist-info/RECORD
