Metadata-Version: 2.1
Name: tikreg
Version: 0.0.1
Summary: tikreg: Tikhonov regression in Python
Home-page: https://gallantlab.github.io/tikreg/
Author: Anwar O. Nunez-Elizalde
Author-email: anwarnunez@gmail.com
License: UNKNOWN
Platform: UNKNOWN
